autotimm/__init__.py
autotimm/backbone.py
autotimm/heads.py
autotimm/loggers.py
autotimm/metrics.py
autotimm/trainer.py
autotimm/utils.py
autotimm/data/__init__.py
autotimm/data/datamodule.py
autotimm/data/dataset.py
autotimm/data/detection_datamodule.py
autotimm/data/detection_dataset.py
autotimm/data/detection_transforms.py
autotimm/data/instance_datamodule.py
autotimm/data/instance_dataset.py
autotimm/data/preset_manager.py
autotimm/data/segmentation_datamodule.py
autotimm/data/segmentation_dataset.py
autotimm/data/segmentation_transforms.py
autotimm/data/timm_transforms.py
autotimm/data/transform_config.py
autotimm/data/transforms.py
autotimm/losses/__init__.py
autotimm/losses/detection.py
autotimm/losses/segmentation.py
autotimm/tasks/__init__.py
autotimm/tasks/classification.py
autotimm/tasks/instance_segmentation.py
autotimm/tasks/object_detection.py
autotimm/tasks/preprocessing_mixin.py
autotimm/tasks/semantic_segmentation.py
autotimm-0.6.2.dist-info/licenses/LICENSE
autotimm-0.6.2.dist-info/METADATA
autotimm-0.6.2.dist-info/WHEEL
autotimm-0.6.2.dist-info/top_level.txt
autotimm-0.6.2.dist-info/RECORD
