Metadata-Version: 2.4
Name: autotimm
Version: 0.6.2
Summary: Automatic Pytorch Image Models
Author: Krishnatheja Vanka
License:                                  Apache License
Project-URL: Homepage, https://github.com/theja-vanka/AutoTimm
Project-URL: Repository, https://github.com/theja-vanka/AutoTimm
Project-URL: Issues, https://github.com/theja-vanka/AutoTimm/issues
Keywords: deep-learning,computer-vision,pytorch,timm,automation,huggingface_hub,torchvision,torchmetrics
Classifier: Development Status :: 3 - Alpha
Classifier: Intended Audience :: Science/Research
Classifier: Programming Language :: Python :: 3
Classifier: Programming Language :: Python :: 3.10
Classifier: Programming Language :: Python :: 3.11
Classifier: Programming Language :: Python :: 3.12
Classifier: Programming Language :: Python :: 3.13
Classifier: Programming Language :: Python :: 3.14
Classifier: Topic :: Scientific/Engineering :: Artificial Intelligence
Requires-Python: >=3.10
License-File: LICENSE
Requires-Dist: torch>=2.0
Requires-Dist: torchvision>=0.15
Requires-Dist: timm>=1.0
Requires-Dist: pytorch-lightning>=2.0
Requires-Dist: torchmetrics>=1.0
Requires-Dist: numpy>=1.23
Requires-Dist: opencv-python-headless>=4.8
Requires-Dist: huggingface_hub>=0.20
Requires-Dist: watermark>=2.3
Requires-Dist: rich>=13.0
Requires-Dist: albumentations>=1.3
Requires-Dist: pycocotools>=2.0
Provides-Extra: tensorboard
Requires-Dist: tensorboard>=2.14; extra == "tensorboard"
Provides-Extra: mlflow
Requires-Dist: mlflow>=2.0; extra == "mlflow"
Provides-Extra: wandb
Requires-Dist: wandb>=0.15; extra == "wandb"
Provides-Extra: all
Requires-Dist: tensorboard>=2.14; extra == "all"
Requires-Dist: mlflow>=2.0; extra == "all"
Requires-Dist: wandb>=0.15; extra == "all"
Requires-Dist: albumentations>=1.3; extra == "all"
Requires-Dist: opencv-python-headless>=4.8; extra == "all"
Requires-Dist: pycocotools>=2.0; extra == "all"
Provides-Extra: dev
Requires-Dist: pytest>=7.0; extra == "dev"
Requires-Dist: pytest-cov; extra == "dev"
Requires-Dist: build; extra == "dev"
Requires-Dist: twine; extra == "dev"
Requires-Dist: ruff; extra == "dev"
Requires-Dist: black; extra == "dev"
Requires-Dist: pycocotools>=2.0; extra == "dev"
Provides-Extra: docs
Requires-Dist: mkdocs>=1.5; extra == "docs"
Requires-Dist: mkdocs-material>=9.0; extra == "docs"
Requires-Dist: mkdocstrings[python]>=0.24; extra == "docs"
Dynamic: license-file
